{
  "schemaVersion": 1,
  "id": "scrap",
  "version": "${version}",

  "name": "Scrap",
  "description": "A technology mod revolving arround scraps.",
  "authors": [
    "Ftoy"
  ],
  "contact": {
    "homepage": "https://fabricmc.net/",
    "sources": "https://github.com/FabricMC/fabric-example-mod"
  },

  "license": "CC0-1.0",
  "icon": "assets/scrap/icon.png",

  "environment": "*",
  "entrypoints": {
    "main": [
      "net.fabricmc.scrap.Main"
    ], "client": [
      "net.fabricmc.scrap.ScrapClient"
    ]
  },
  "depends": {
    "fabricloader": ">=0.14.6",
    "fabric": "*",
    "minecraft": "~1.19",
    "java": ">=17"
  },
  "suggests": {
    "another-mod": "*"
  }
}
